jacksonpy/JacksonAlgo.py
jacksonpy/__init__.py
jacksonpy/__main__.py
jacksonpy/data.py
jacksonpy/utils.py
PyJacksonAlgo-0.1.2.dist-info/LICENSE
PyJacksonAlgo-0.1.2.dist-info/METADATA
PyJacksonAlgo-0.1.2.dist-info/WHEEL
PyJacksonAlgo-0.1.2.dist-info/top_level.txt
PyJacksonAlgo-0.1.2.dist-info/RECORD
