Metadata-Version: 2.1
Name: PyJacksonAlgo
Version: 0.1.2
Summary: Python package to solve the job shop scheduling problem with Gantt chart as output
Home-page: https://github.com/th-rpy/jackson_job_shop_scheduling
Author: Saraei Thamer
Author-email: thamer.saraei@polymtl.ca
Project-URL: Bug Tracker, https://github.com/th-rpy/jackson_job_shop_scheduling/issues
Classifier: Programming Language :: Python :: 3
Classifier: License :: OSI Approved :: MIT License
Classifier: Operating System :: OS Independent
Requires-Python: >=3.6
License-File: LICENSE
